ProfessorRegressor/__init__.py
ProfessorRegressor/professorRegressor.py
ProfessorRegressor-1.1.dist-info/LICENSE.txt
ProfessorRegressor-1.1.dist-info/METADATA
ProfessorRegressor-1.1.dist-info/WHEEL
ProfessorRegressor-1.1.dist-info/top_level.txt
ProfessorRegressor-1.1.dist-info/RECORD
