Metadata-Version: 2.1
Name: ProfessorRegressor
Version: 1.1
Summary: Statistical python model for comparison of species using pairwise regression
Home-page: https://github.com/chdwck9/professorRegressor
Author: Susan & Richard Dykes
Author-email: chdwck9@gmail.com
License: UNKNOWN
Platform: UNKNOWN
Classifier: Programming Language :: Python :: 3
Classifier: License :: OSI Approved :: MIT License
Classifier: Operating System :: OS Independent
Requires-Python: >=3.0
